pylistenbrainz/__init__.py
pylistenbrainz/client.py
pylistenbrainz/errors.py
pylistenbrainz/listen.py
pylistenbrainz/utils.py
pylistenbrainz/tests/__init__.py
pylistenbrainz/tests/test_client.py
pylistenbrainz/tests/testdata/get_listens_happy_path_response.json
pylistenbrainz/tests/testdata/get_playing_now_happy_path_response.json
pylistenbrainz/tests/testdata/good_submit_listens_response.json
pylistenbrainz/tests/testdata/no_playing_now.json
pylistenbrainz/tests/testdata/token_validity_bad_token_response.json
pylistenbrainz/tests/testdata/token_validity_good_token_response.json
gcrkrause_pylistenbrainz2-0.5.5a7.dist-info/LICENSE
gcrkrause_pylistenbrainz2-0.5.5a7.dist-info/METADATA
gcrkrause_pylistenbrainz2-0.5.5a7.dist-info/WHEEL
gcrkrause_pylistenbrainz2-0.5.5a7.dist-info/top_level.txt
gcrkrause_pylistenbrainz2-0.5.5a7.dist-info/RECORD
