Metadata-Version: 2.1
Name: gcrkrause-pylistenbrainz2
Version: 0.5.5a7
Summary: A simple ListenBrainz client library for Python
Author-email: Param Singh <iliekcomputers@gmail.com>
Project-URL: Homepage, https://github.com/paramsingh/pylistenbrainz
Classifier: Programming Language :: Python :: 3
Classifier: License :: OSI Approved :: GNU General Public License v3 (GPLv3)
Classifier: Operating System :: OS Independent
Requires-Python: >=3.8
License-File: LICENSE
Requires-Dist: requests >=2.31.0
Requires-Dist: importlib-metadata >=3.10.0 ; python_version < "3.10"
Provides-Extra: build
Requires-Dist: build ; extra == 'build'
Requires-Dist: twine ; extra == 'build'
Provides-Extra: docs
Requires-Dist: sphinx ==3.0.1 ; extra == 'docs'
Provides-Extra: tests
Requires-Dist: pytest ==5.4.1 ; extra == 'tests'
Requires-Dist: pytest-cov ==2.8.1 ; extra == 'tests'
